MANIFEST.in
README.md
eicar.com
setup.py
eicar_pack_10/__init__.py
eicar_pack_10/eic_py_.py
eicar_pack_10/eicar.com
malware_test_pack.egg-info/PKG-INFO
malware_test_pack.egg-info/SOURCES.txt
malware_test_pack.egg-info/dependency_links.txt
malware_test_pack.egg-info/top_level.txt